{"Abilene-Sweetwater TX": {"NFL": 45, "NBA": 21, "MLB": 14, "NHL": 2, "NASCAR": 4, "CBB": 3, "CFB": 11, "most": "NHL"}, "Albany GA": {"NFL": 32, "NBA": 30, "MLB": 9, "NHL": 1, "NASCAR": 8, "CBB": 3, "CFB": 17, "most": "NHL"}, "Albany-Schenectady-Troy NY": {"NFL": 40, "NBA": 20, "MLB": 20, "NHL": 8, "NASCAR": 6, "CBB": 3, "CFB": 4, "most": "CBB"}, "Albuquerque-Santa Fe NM": {"NFL": 53, "NBA": 21, "MLB": 11, "NHL": 3, "NASCAR": 3, "CBB": 4, "CFB": 6, "most": "NHL"}, "Alexandria LA": {"NFL": 42, "NBA": 28, "MLB": 9, "NHL": 1, "NASCAR": 5, "CBB": 3, "CFB": 12, "most": "NHL"}, "Alpena MI": {"NFL": 28, "NBA": 13, "MLB": 21, "NHL": 12, "NASCAR": 10, "CBB": 7, "CFB": 9, "most": "CBB"}, "Amarillo TX": {"NFL": 47, "NBA": 22, "MLB": 12, "NHL": 2, "NASCAR": 5, "CBB": 3, "CFB": 10, "most": "NHL"}, "Atlanta GA": {"NFL": 36, "NBA": 28, "MLB": 10, "NHL": 3, "NASCAR": 5, "CBB": 5, "CFB": 14, "most": "NHL"}, "Augusta GA": {"NFL": 39, "NBA": 26, "MLB": 8, "NHL": 3, "NASCAR": 8, "CBB": 4, "CFB": 13, "most": "NHL"}, "Austin TX": {"NFL": 40, "NBA": 29, "MLB": 11, "NHL": 3, "NASCAR": 3, "CBB": 3, "CFB": 11, "most": "NHL"}, "Bakersfield CA": {"NFL": 48, "NBA": 26, "MLB": 14, "NHL": 3, "NASCAR": 4, "CBB": 1, "CFB": 3, "most": "CBB"}, "Baltimore MD": {"NFL": 45, "NBA": 20, "MLB": 20, "NHL": 5, "NASCAR": 3, "CBB": 3, "CFB": 4, "most": "NASCAR"}, "Bangor ME": {"NFL": 39, "NBA": 20, "MLB": 19, "NHL": 9, "NASCAR": 8, "CBB": 2, "CFB": 3, "most": "CBB"}, "Baton Rouge LA": {"NFL": 40, "NBA": 29, "MLB": 8, "NHL": 2, "NASCAR": 3, "CBB": 3, "CFB": 15, "most": "NHL"}, "Beaumont-Port Arthur TX": {"NFL": 45, "NBA": 27, "MLB": 12, "NHL": 1, "NASCAR": 4, "CBB": 2, "CFB": 9, "most": "NHL"}, "Bend OR": {"NFL": 39, "NBA": 24, "MLB": 13, "NHL": 4, "NASCAR": 4, "CBB": 3, "CFB": 13, "most": "CBB"}, "Billings MT": {"NFL": 50, "NBA": 17, "MLB": 12, "NHL": 5, "NASCAR": 5, "CBB": 4, "CFB": 7, "most": "CBB"}, "Biloxi-Gulfport MS": {"NFL": 43, "NBA": 23, "MLB": 9, "NHL": 2, "NASCAR": 6, "CBB": 3, "CFB": 14, "most": "NHL"}, "Binghamton NY": {"NFL": 41, "NBA": 19, "MLB": 17, "NHL": 9, "NASCAR": 7, "CBB": 3, "CFB": 4, "most": "CBB"}, "Birmingham AL": {"NFL": 26, "NBA": 22, "MLB": 10, "NHL": 2, "NASCAR": 6, "CBB": 6, "CFB": 27, "most": "NHL"}, "Bluefield-Beckley-Oak Hill WV": {"NFL": 34, "NBA": 20, "MLB": 10, "NHL": 2, "NASCAR": 13, "CBB": 6, "CFB": 14, "most": "NHL"}, "Boise ID": {"NFL": 43, "NBA": 20, "MLB": 11, "NHL": 4, "NASCAR": 4, "CBB": 4, "CFB": 14, "most": "NHL"}, "Boston MA-Manchester NH": {"NFL": 37, "NBA": 25, "MLB": 17, "NHL": 12, "NASCAR": 3, "CBB": 2, "CFB": 3, "most": "CBB"}, "Bowling Green KY": {"NFL": 36, "NBA": 18, "MLB": 10, "NHL": 4, "NASCAR": 6, "CBB": 16, "CFB": 11, "most": "NHL"}, "Buffalo NY": {"NFL": 41, "NBA": 16, "MLB": 11, "NHL": 23, "NASCAR": 4, "CBB": 2, "CFB": 3, "most": "CBB"}, "Burlington VT-Plattsburgh NY": {"NFL": 36, "NBA": 19, "MLB": 18, "NHL": 14, "NASCAR": 7, "CBB": 3, "CFB": 3, "most": "CBB"}, "Butte-Bozeman MT": {"NFL": 48, "NBA": 17, "MLB": 12, "NHL": 8, "NASCAR": 4, "CBB": 4, "CFB": 8, "most": "NASCAR"}, "Casper-Riverton WY": {"NFL": 53, "NBA": 16, "MLB": 10, "NHL": 5, "NASCAR": 5, "CBB": 4, "CFB": 7, "most": "CBB"}, "Cedar Rapids-Waterloo-Iowa City & Dubuque IA": {"NFL": 39, "NBA": 20, "MLB": 15, "NHL": 4, "NASCAR": 6, "CBB": 6, "CFB": 10, "most": "NHL"}, "Champaign & Springfield-Decatur IL": {"NFL": 30, "NBA": 24, "MLB": 25, "NHL": 6, "NASCAR": 6, "CBB": 5, "CFB": 5, "most": "CBB"}, "Charleston SC": {"NFL": 40, "NBA": 22, "MLB": 10, "NHL": 4, "NASCAR": 6, "CBB": 5, "CFB": 14, "most": "NHL"}, "Charleston-Huntington WV": {"NFL": 33, "NBA": 19, "MLB": 10, "NHL": 3, "NASCAR": 10, "CBB": 14, "CFB": 12, "most": "NHL"}, "Charlotte NC": {"NFL": 41, "NBA": 23, "MLB": 9, "NHL": 3, "NASCAR": 10, "CBB": 6, "CFB": 8, "most": "NHL"}, "Charlottesville VA": {"NFL": 37, "NBA": 22, "MLB": 12, "NHL": 5, "NASCAR": 7, "CBB": 8, "CFB": 9, "most": "NHL"}, "Chattanooga TN": {"NFL": 31, "NBA": 21, "MLB": 11, "NHL": 3, "NASCAR": 9, "CBB": 4, "CFB": 20, "most": "NHL"}, "Cheyenne WY-Scottsbluff NE": {"NFL": 51, "NBA": 16, "MLB": 11, "NHL": 5, "NASCAR": 5, "CBB": 3, "CFB": 10, "most": "CBB"}, "Chicago IL": {"NFL": 33, "NBA": 28, "MLB": 19, "NHL": 10, "NASCAR": 3, "CBB": 4, "CFB": 5, "most": "NASCAR"}, "Chico-Redding CA": {"NFL": 44, "NBA": 24, "MLB": 18, "NHL": 3, "NASCAR": 5, "CBB": 2, "CFB": 4, "most": "CBB"}, "Cincinnati OH": {"NFL": 38, "NBA": 20, "MLB": 16, "NHL": 4, "NASCAR": 5, "CBB": 10, "CFB": 8, "most": "NHL"}, "Clarksburg-Weston WV": {"NFL": 35, "NBA": 17, "MLB": 12, "NHL": 5, "NASCAR": 10, "CBB": 8, "CFB": 14, "most": "NHL"}, "Cleveland-Akron (Canton) OH": {"NFL": 34, "NBA": 33, "MLB": 16, "NHL": 3, "NASCAR": 4, "CBB": 2, "CFB": 7, "most": "CBB"}, "Colorado Springs-Pueblo CO": {"NFL": 52, "NBA": 17, "MLB": 12, "NHL": 6, "NASCAR": 3, "CBB": 3, "CFB": 7, "most": "NASCAR"}, "Columbia SC": {"NFL": 36, "NBA": 26, "MLB": 8, "NHL": 2, "NASCAR": 6, "CBB": 4, "CFB": 17, "most": "NHL"}, "Columbia-Jefferson City MO": {"NFL": 33, "NBA": 19, "MLB": 23, "NHL": 6, "NASCAR": 6, "CBB": 5, "CFB": 8, "most": "CBB"}, "Columbus GA": {"NFL": 30, "NBA": 27, "MLB": 9, "NHL": 2, "NASCAR": 5, "CBB": 6, "CFB": 21, "most": "NHL"}, "Columbus OH": {"NFL": 33, "NBA": 24, "MLB": 12, "NHL": 8, "NASCAR": 5, "CBB": 5, "CFB": 13, "most": "NASCAR"}, "Columbus-Tupelo-West Point MS": {"NFL": 39, "NBA": 23, "MLB": 9, "NHL": 2, "NASCAR": 6, "CBB": 4, "CFB": 16, "most": "NHL"}, "Corpus Christi TX": {"NFL": 47, "NBA": 29, "MLB": 10, "NHL": 2, "NASCAR": 3, "CBB": 2, "CFB": 7, "most": "NHL"}, "Dallas-Ft. Worth TX": {"NFL": 40, "NBA": 28, "MLB": 13, "NHL": 3, "NASCAR": 3, "CBB": 3, "CFB": 10, "most": "NHL"}, "Davenport IA-Rock Island-Moline IL": {"NFL": 38, "NBA": 18, "MLB": 21, "NHL": 5, "NASCAR": 7, "CBB": 4, "CFB": 7, "most": "CBB"}, "Dayton OH": {"NFL": 40, "NBA": 21, "MLB": 12, "NHL": 4, "NASCAR": 6, "CBB": 6, "CFB": 10, "most": "NHL"}, "Denver CO": {"NFL": 49, "NBA": 19, "MLB": 13, "NHL": 7, "NASCAR": 3, "CBB": 3, "CFB": 6, "most": "NASCAR"}, "Des Moines-Ames IA": {"NFL": 39, "NBA": 19, "MLB": 15, "NHL": 4, "NASCAR": 7, "CBB": 7, "CFB": 10, "most": "NHL"}, "Detroit MI": {"NFL": 30, "NBA": 26, "MLB": 16, "NHL": 10, "NASCAR": 3, "CBB": 6, "CFB": 9, "most": "NASCAR"}, "Dothan AL": {"NFL": 29, "NBA": 21, "MLB": 8, "NHL": 2, "NASCAR": 7, "CBB": 4, "CFB": 29, "most": "NHL"}, "Duluth MN-Superior WI": {"NFL": 43, "NBA": 15, "MLB": 13, "NHL": 18, "NASCAR": 5, "CBB": 3, "CFB": 4, "most": "CBB"}, "El Paso TX": {"NFL": 54, "NBA": 25, "MLB": 10, "NHL": 2, "NASCAR": 2, "CBB": 2, "CFB": 5, "most": "NHL"}, "Elmira NY": {"NFL": 44, "NBA": 14, "MLB": 15, "NHL": 7, "NASCAR": 12, "CBB": 3, "CFB": 4, "most": "CBB"}, "Erie PA": {"NFL": 44, "NBA": 16, "MLB": 15, "NHL": 12, "NASCAR": 6, "CBB": 3, "CFB": 5, "most": "CBB"}, "Eugene OR": {"NFL": 34, "NBA": 28, "MLB": 12, "NHL": 3, "NASCAR": 4, "CBB": 4, "CFB": 15, "most": "NHL"}, "Eureka CA": {"NFL": 37, "NBA": 26, "MLB": 23, "NHL": 3, "NASCAR": 4, "CBB": 2, "CFB": 4, "most": "CBB"}, "Evansville IN": {"NFL": 30, "NBA": 21, "MLB": 14, "NHL": 3, "NASCAR": 7, "CBB": 19, "CFB": 5, "most": "NHL"}, "Fargo-Valley City ND": {"NFL": 44, "NBA": 18, "MLB": 12, "NHL": 13, "NASCAR": 5, "CBB": 3, "CFB": 6, "most": "CBB"}, "Flint-Saginaw-Bay City MI": {"NFL": 31, "NBA": 20, "MLB": 16, "NHL": 8, "NASCAR": 7, "CBB": 8, "CFB": 9, "most": "NASCAR"}, "Florence-Myrtle Beach SC": {"NFL": 37, "NBA": 22, "MLB": 12, "NHL": 3, "NASCAR": 10, "CBB": 5, "CFB": 11, "most": "NHL"}, "Fresno-Visalia CA": {"NFL": 46, "NBA": 26, "MLB": 15, "NHL": 4, "NASCAR": 3, "CBB": 2, "CFB": 4, "most": "CBB"}, "Ft. Myers-Naples FL": {"NFL": 38, "NBA": 21, "MLB": 15, "NHL": 8, "NASCAR": 5, "CBB": 5, "CFB": 8, "most": "NASCAR"}, "Ft. Smith-Fayetteville-Springdale-Rogers AR": {"NFL": 35, "NBA": 25, "MLB": 12, "NHL": 3, "NASCAR": 5, "CBB": 5, "CFB": 16, "most": "NHL"}, "Ft. Wayne IN": {"NFL": 39, "NBA": 21, "MLB": 14, "NHL": 5, "NASCAR": 7, "CBB": 7, "CFB": 7, "most": "NHL"}, "Gainesville FL": {"NFL": 32, "NBA": 26, "MLB": 9, "NHL": 4, "NASCAR": 4, "CBB": 5, "CFB": 19, "most": "NHL"}, "Glendive MT": {"NFL": 56, "NBA": 14, "MLB": 13, "NHL": 0, "NASCAR": 9, "CBB": 3, "CFB": 4, "most": "NHL"}, "Grand Junction-Montrose CO": {"NFL": 54, "NBA": 15, "MLB": 12, "NHL": 5, "NASCAR": 5, "CBB": 3, "CFB": 6, "most": "CBB"}, "Grand Rapids-Kalamazoo-Battle Creek MI": {"NFL": 30, "NBA": 19, "MLB": 16, "NHL": 8, "NASCAR": 6, "CBB": 10, "CFB": 10, "most": "NASCAR"}, "Great Falls MT": {"NFL": 50, "NBA": 19, "MLB": 11, "NHL": 5, "NASCAR": 5, "CBB": 3, "CFB": 6, "most": "CBB"}, "Green Bay-Appleton WI": {"NFL": 51, "NBA": 16, "MLB": 14, "NHL": 4, "NASCAR": 6, "CBB": 3, "CFB": 5, "most": "CBB"}, "Greensboro-High Point-Winston Salem NC": {"NFL": 38, "NBA": 23, "MLB": 9, "NHL": 3, "NASCAR": 10, "CBB": 9, "CFB": 7, "most": "NHL"}, "Greenville-New Bern-Washington NC": {"NFL": 40, "NBA": 21, "MLB": 11, "NHL": 4, "NASCAR": 9, "CBB": 7, "CFB": 9, "most": "NHL"}, "Greenville-Spartanburg SC-Asheville NC-Anderson SC": {"NFL": 34, "NBA": 20, "MLB": 11, "NHL": 3, "NASCAR": 9, "CBB": 6, "CFB": 17, "most": "NHL"}, "Greenwood-Greenville MS": {"NFL": 33, "NBA": 39, "MLB": 8, "NHL": 1, "NASCAR": 3, "CBB": 4, "CFB": 12, "most": "NHL"}, "Harlingen-Weslaco-Brownsville-McAllen TX": {"NFL": 50, "NBA": 33, "MLB": 10, "NHL": 1, "NASCAR": 2, "CBB": 1, "CFB": 4, "most": "NHL"}, "Harrisburg-Lancaster-Lebanon-York PA": {"NFL": 43, "NBA": 16, "MLB": 17, "NHL": 9, "NASCAR": 7, "CBB": 3, "CFB": 6, "most": "CBB"}, "Harrisonburg VA": {"NFL": 42, "NBA": 20, "MLB": 12, "NHL": 5, "NASCAR": 8, "CBB": 5, "CFB": 7, "most": "NHL"}, "Hartford & New Haven CT": {"NFL": 38, "NBA": 24, "MLB": 19, "NHL": 8, "NASCAR": 4, "CBB": 3, "CFB": 4, "most": "CBB"}, "Hattiesburg-Laurel MS": {"NFL": 40, "NBA": 24, "MLB": 8, "NHL": 1, "NASCAR": 5, "CBB": 3, "CFB": 20, "most": "NHL"}, "Helena MT": {"NFL": 52, "NBA": 15, "MLB": 11, "NHL": 6, "NASCAR": 4, "CBB": 4, "CFB": 8, "most": "NASCAR"}, "Honolulu HI": {"NFL": 43, "NBA": 29, "MLB": 11, "NHL": 4, "NASCAR": 1, "CBB": 3, "CFB": 8, "most": "NASCAR"}, "Houston TX": {"NFL": 42, "NBA": 32, "MLB": 12, "NHL": 2, "NASCAR": 2, "CBB": 2, "CFB": 8, "most": "NHL"}, "Huntsville-Decatur (Florence) AL": {"NFL": 27, "NBA": 22, "MLB": 9, "NHL": 3, "NASCAR": 7, "CBB": 5, "CFB": 27, "most": "NHL"}, "Idaho Falls-Pocatello ID": {"NFL": 44, "NBA": 24, "MLB": 10, "NHL": 5, "NASCAR": 4, "CBB": 3, "CFB": 9, "most": "CBB"}, "Indianapolis IN": {"NFL": 37, "NBA": 28, "MLB": 12, "NHL": 3, "NASCAR": 6, "CBB": 7, "CFB": 6, "most": "NHL"}, "Jackson MS": {"NFL": 38, "NBA": 31, "MLB": 8, "NHL": 1, "NASCAR": 4, "CBB": 4, "CFB": 15, "most": "NHL"}, "Jackson TN": {"NFL": 32, "NBA": 28, "MLB": 13, "NHL": 2, "NASCAR": 7, "CBB": 5, "CFB": 13, "most": "NHL"}, "Jacksonville FL": {"NFL": 42, "NBA": 23, "MLB": 9, "NHL": 4, "NASCAR": 5, "CBB": 3, "CFB": 13, "most": "CBB"}, "Johnstown-Altoona PA": {"NFL": 37, "NBA": 14, "MLB": 17, "NHL": 13, "NASCAR": 6, "CBB": 3, "CFB": 9, "most": "CBB"}, "Jonesboro AR": {"NFL": 31, "NBA": 28, "MLB": 15, "NHL": 2, "NASCAR": 7, "CBB": 5, "CFB": 14, "most": "NHL"}, "Joplin MO-Pittsburg KS": {"NFL": 41, "NBA": 18, "MLB": 18, "NHL": 2, "NASCAR": 7, "CBB": 6, "CFB": 8, "most": "NHL"}, "Kansas City MO": {"NFL": 36, "NBA": 18, "MLB": 25, "NHL": 3, "NASCAR": 4, "CBB": 8, "CFB": 6, "most": "NHL"}, "Knoxville TN": {"NFL": 32, "NBA": 19, "MLB": 11, "NHL": 4, "NASCAR": 10, "CBB": 7, "CFB": 17, "most": "NHL"}, "La Crosse-Eau Claire WI": {"NFL": 48, "NBA": 16, "MLB": 14, "NHL": 6, "NASCAR": 6, "CBB": 4, "CFB": 5, "most": "CBB"}, "Lafayette IN": {"NFL": 33, "NBA": 30, "MLB": 13, "NHL": 5, "NASCAR": 4, "CBB": 8, "CFB": 7, "most": "NASCAR"}, "Lafayette LA": {"NFL": 45, "NBA": 28, "MLB": 8, "NHL": 2, "NASCAR": 3, "CBB": 3, "CFB": 13, "most": "NHL"}, "Lake Charles LA": {"NFL": 43, "NBA": 27, "MLB": 9, "NHL": 2, "NASCAR": 4, "CBB": 2, "CFB": 12, "most": "NHL"}, "Lansing MI": {"NFL": 26, "NBA": 21, "MLB": 13, "NHL": 8, "NASCAR": 5, "CBB": 16, "CFB": 11, "most": "NASCAR"}, "Laredo TX": {"NFL": 44, "NBA": 39, "MLB": 10, "NHL": 2, "NASCAR": 1, "CBB": 1, "CFB": 3, "most": "NASCAR"}, "Las Vegas NV": {"NFL": 38, "NBA": 27, "MLB": 16, "NHL": 6, "NASCAR": 3, "CBB": 4, "CFB": 6, "most": "NASCAR"}, "Lexington KY": {"NFL": 22, "NBA": 20, "MLB": 8, "NHL": 2, "NASCAR": 6, "CBB": 35, "CFB": 7, "most": "NHL"}, "Lima OH": {"NFL": 36, "NBA": 22, "MLB": 13, "NHL": 3, "NASCAR": 8, "CBB": 5, "CFB": 14, "most": "NHL"}, "Lincoln & Hastings-Kearney NE": {"NFL": 33, "NBA": 19, "MLB": 13, "NHL": 3, "NASCAR": 6, "CBB": 5, "CFB": 20, "most": "NHL"}, "Little Rock-Pine Bluff AR": {"NFL": 32, "NBA": 28, "MLB": 16, "NHL": 2, "NASCAR": 4, "CBB": 4, "CFB": 13, "most": "NHL"}, "Los Angeles CA": {"NFL": 34, "NBA": 35, "MLB": 16, "NHL": 6, "NASCAR": 2, "CBB": 3, "CFB": 5, "most": "NASCAR"}, "Louisville KY": {"NFL": 26, "NBA": 21, "MLB": 9, "NHL": 2, "NASCAR": 6, "CBB": 27, "CFB": 9, "most": "NHL"}, "Lubbock TX": {"NFL": 42, "NBA": 25, "MLB": 12, "NHL": 2, "NASCAR": 3, "CBB": 3, "CFB": 12, "most": "NHL"}, "Macon GA": {"NFL": 34, "NBA": 29, "MLB": 10, "NHL": 2, "NASCAR": 7, "CBB": 4, "CFB": 14, "most": "NHL"}, "Madison WI": {"NFL": 43, "NBA": 18, "MLB": 14, "NHL": 5, "NASCAR": 7, "CBB": 5, "CFB": 8, "most": "NHL"}, "Mankato MN": {"NFL": 44, "NBA": 18, "MLB": 14, "NHL": 12, "NASCAR": 4, "CBB": 3, "CFB": 4, "most": "CBB"}, "Marquette MI": {"NFL": 41, "NBA": 13, "MLB": 15, "NHL": 16, "NASCAR": 5, "CBB": 4, "CFB": 5, "most": "CBB"}, "Medford-Klamath Falls OR": {"NFL": 42, "NBA": 23, "MLB": 15, "NHL": 3, "NASCAR": 5, "CBB": 3, "CFB": 10, "most": "NHL"}, "Memphis TN": {"NFL": 33, "NBA": 36, "MLB": 9, "NHL": 2, "NASCAR": 4, "CBB": 5, "CFB": 11, "most": "NHL"}, "Meridian MS": {"NFL": 28, "NBA": 29, "MLB": 14, "NHL": 2, "NASCAR": 5, "CBB": 5, "CFB": 17, "most": "NHL"}, "Miami-Ft. Lauderdale FL": {"NFL": 31, "NBA": 41, "MLB": 13, "NHL": 4, "NASCAR": 2, "CBB": 2, "CFB": 6, "most": "NASCAR"}, "Milwaukee WI": {"NFL": 42, "NBA": 25, "MLB": 16, "NHL": 5, "NASCAR": 4, "CBB": 4, "CFB": 5, "most": "NASCAR"}, "Minneapolis-St. Paul MN": {"NFL": 41, "NBA": 21, "MLB": 14, "NHL": 13, "NASCAR": 4, "CBB": 3, "CFB": 5, "most": "CBB"}, "Minot-Bismarck-Dickinson(Williston) ND": {"NFL": 50, "NBA": 17, "MLB": 11, "NHL": 8, "NASCAR": 6, "CBB": 3, "CFB": 5, "most": "CBB"}, "Missoula MT": {"NFL": 49, "NBA": 17, "MLB": 12, "NHL": 6, "NASCAR": 4, "CBB": 4, "CFB": 8, "most": "NASCAR"}, "Mobile AL-Pensacola (Ft. Walton Beach) FL": {"NFL": 34, "NBA": 21, "MLB": 10, "NHL": 3, "NASCAR": 6, "CBB": 4, "CFB": 22, "most": "NHL"}, "Monroe LA-El Dorado AR": {"NFL": 38, "NBA": 31, "MLB": 9, "NHL": 1, "NASCAR": 5, "CBB": 3, "CFB": 13, "most": "NHL"}, "Monterey-Salinas CA": {"NFL": 38, "NBA": 31, "MLB": 19, "NHL": 5, "NASCAR": 2, "CBB": 2, "CFB": 4, "most": "NASCAR"}, "Montgomery (Selma) AL": {"NFL": 24, "NBA": 28, "MLB": 8, "NHL": 1, "NASCAR": 5, "CBB": 6, "CFB": 27, "most": "NHL"}, "Nashville TN": {"NFL": 35, "NBA": 21, "MLB": 10, "NHL": 7, "NASCAR": 6, "CBB": 8, "CFB": 13, "most": "NASCAR"}, "New Orleans LA": {"NFL": 45, "NBA": 28, "MLB": 8, "NHL": 2, "NASCAR": 3, "CBB": 3, "CFB": 11, "most": "NHL"}, "New York NY": {"NFL": 32, "NBA": 32, "MLB": 19, "NHL": 9, "NASCAR": 2, "CBB": 3, "CFB": 3, "most": "NASCAR"}, "Norfolk-Portsmouth-Newport News VA": {"NFL": 47, "NBA": 23, "MLB": 11, "NHL": 4, "NASCAR": 5, "CBB": 4, "CFB": 6, "most": "NHL"}, "North Platte NE": {"NFL": 38, "NBA": 17, "MLB": 10, "NHL": 2, "NASCAR": 7, "CBB": 5, "CFB": 21, "most": "NHL"}, "Odessa-Midland TX": {"NFL": 48, "NBA": 24, "MLB": 12, "NHL": 2, "NASCAR": 4, "CBB": 2, "CFB": 9, "most": "NHL"}, "Oklahoma City OK": {"NFL": 32, "NBA": 33, "MLB": 9, "NHL": 3, "NASCAR": 4, "CBB": 3, "CFB": 15, "most": "NHL"}, "Omaha NE": {"NFL": 34, "NBA": 20, "MLB": 14, "NHL": 4, "NASCAR": 5, "CBB": 6, "CFB": 16, "most": "NHL"}, "Orlando-Daytona Beach-Melbourne FL": {"NFL": 35, "NBA": 28, "MLB": 14, "NHL": 5, "NASCAR": 5, "CBB": 3, "CFB": 10, "most": "CBB"}, "Ottumwa IA-Kirksville MO": {"NFL": 37, "NBA": 16, "MLB": 18, "NHL": 4, "NASCAR": 11, "CBB": 9, "CFB": 6, "most": "NHL"}, "Paducah KY-Cape Girardeau MO-Harrisburg-Mount Vernon IL": {"NFL": 29, "NBA": 21, "MLB": 22, "NHL": 4, "NASCAR": 7, "CBB": 11, "CFB": 6, "most": "NHL"}, "Palm Springs CA": {"NFL": 41, "NBA": 23, "MLB": 16, "NHL": 9, "NASCAR": 3, "CBB": 3, "CFB": 5, "most": "NASCAR"}, "Panama City FL": {"NFL": 32, "NBA": 19, "MLB": 10, "NHL": 4, "NASCAR": 7, "CBB": 4, "CFB": 23, "most": "NHL"}, "Parkersburg WV": {"NFL": 36, "NBA": 18, "MLB": 11, "NHL": 4, "NASCAR": 11, "CBB": 6, "CFB": 13, "most": "NHL"}, "Peoria-Bloomington IL": {"NFL": 33, "NBA": 21, "MLB": 26, "NHL": 7, "NASCAR": 5, "CBB": 4, "CFB": 4, "most": "CBB"}, "Philadelphia PA": {"NFL": 40, "NBA": 25, "MLB": 15, "NHL": 9, "NASCAR": 3, "CBB": 3, "CFB": 4, "most": "NASCAR"}, "Phoenix AZ": {"NFL": 44, "NBA": 23, "MLB": 15, "NHL": 6, "NASCAR": 3, "CBB": 4, "CFB": 6, "most": "NASCAR"}, "Pittsburgh PA": {"NFL": 33, "NBA": 13, "MLB": 19, "NHL": 20, "NASCAR": 4, "CBB": 5, "CFB": 6, "most": "NASCAR"}, "Portland OR": {"NFL": 33, "NBA": 33, "MLB": 16, "NHL": 5, "NASCAR": 3, "CBB": 3, "CFB": 8, "most": "NASCAR"}, "Portland-Auburn ME": {"NFL": 39, "NBA": 19, "MLB": 19, "NHL": 10, "NASCAR": 7, "CBB": 2, "CFB": 3, "most": "CBB"}, "Presque Isle ME": {"NFL": 31, "NBA": 26, "MLB": 18, "NHL": 11, "NASCAR": 9, "CBB": 3, "CFB": 2, "most": "CFB"}, "Providence RI-New Bedford MA": {"NFL": 41, "NBA": 24, "MLB": 18, "NHL": 10, "NASCAR": 3, "CBB": 3, "CFB": 3, "most": "NASCAR"}, "Quincy IL-Hannibal MO-Keokuk IA": {"NFL": 34, "NBA": 18, "MLB": 27, "NHL": 5, "NASCAR": 7, "CBB": 4, "CFB": 5, "most": "CBB"}, "Raleigh-Durham (Fayetteville) NC": {"NFL": 37, "NBA": 25, "MLB": 10, "NHL": 5, "NASCAR": 6, "CBB": 10, "CFB": 7, "most": "NHL"}, "Rapid City SD": {"NFL": 51, "NBA": 17, "MLB": 12, "NHL": 5, "NASCAR": 5, "CBB": 3, "CFB": 6, "most": "CBB"}, "Reno NV": {"NFL": 42, "NBA": 22, "MLB": 19, "NHL": 5, "NASCAR": 3, "CBB": 3, "CFB": 6, "most": "NASCAR"}, "Richmond-Petersburg VA": {"NFL": 43, "NBA": 24, "MLB": 11, "NHL": 4, "NASCAR": 6, "CBB": 5, "CFB": 6, "most": "NHL"}, "Roanoke-Lynchburg VA": {"NFL": 35, "NBA": 22, "MLB": 14, "NHL": 5, "NASCAR": 9, "CBB": 6, "CFB": 10, "most": "NHL"}, "Rochester MN-Mason City IA-Austin MN": {"NFL": 45, "NBA": 18, "MLB": 13, "NHL": 9, "NASCAR": 6, "CBB": 3, "CFB": 6, "most": "CBB"}, "Rochester NY": {"NFL": 44, "NBA": 18, "MLB": 16, "NHL": 11, "NASCAR": 4, "CBB": 3, "CFB": 3, "most": "CBB"}, "Rockford IL": {"NFL": 40, "NBA": 21, "MLB": 20, "NHL": 7, "NASCAR": 5, "CBB": 3, "CFB": 4, "most": "CBB"}, "Sacramento-Stockton-Modesto CA": {"NFL": 40, "NBA": 33, "MLB": 16, "NHL": 3, "NASCAR": 3, "CBB": 2, "CFB": 4, "most": "CBB"}, "Salisbury MD": {"NFL": 44, "NBA": 18, "MLB": 20, "NHL": 5, "NASCAR": 6, "CBB": 3, "CFB": 4, "most": "CBB"}, "Salt Lake City UT": {"NFL": 39, "NBA": 32, "MLB": 10, "NHL": 4, "NASCAR": 3, "CBB": 3, "CFB": 10, "most": "NASCAR"}, "San Angelo TX": {"NFL": 46, "NBA": 24, "MLB": 11, "NHL": 2, "NASCAR": 4, "CBB": 2, "CFB": 11, "most": "NHL"}, "San Antonio TX": {"NFL": 39, "NBA": 39, "MLB": 9, "NHL": 2, "NASCAR": 2, "CBB": 2, "CFB": 7, "most": "NHL"}, "San Diego CA": {"NFL": 43, "NBA": 26, "MLB": 16, "NHL": 5, "NASCAR": 2, "CBB": 3, "CFB": 5, "most": "NASCAR"}, "San Francisco-Oakland-San Jose CA": {"NFL": 34, "NBA": 36, "MLB": 17, "NHL": 5, "NASCAR": 2, "CBB": 2, "CFB": 4, "most": "NASCAR"}, "Santa Barbara-Santa Maria-San Luis Obispo CA": {"NFL": 38, "NBA": 30, "MLB": 17, "NHL": 5, "NASCAR": 2, "CBB": 3, "CFB": 5, "most": "NASCAR"}, "Savannah GA": {"NFL": 37, "NBA": 26, "MLB": 11, "NHL": 4, "NASCAR": 6, "CBB": 4, "CFB": 13, "most": "NHL"}, "Seattle-Tacoma WA": {"NFL": 47, "NBA": 21, "MLB": 13, "NHL": 4, "NASCAR": 2, "CBB": 3, "CFB": 10, "most": "NASCAR"}, "Sherman TX-Ada OK": {"NFL": 38, "NBA": 25, "MLB": 13, "NHL": 2, "NASCAR": 6, "CBB": 3, "CFB": 13, "most": "NHL"}, "Shreveport LA": {"NFL": 41, "NBA": 28, "MLB": 10, "NHL": 2, "NASCAR": 5, "CBB": 2, "CFB": 11, "most": "NHL"}, "Sioux City IA": {"NFL": 40, "NBA": 18, "MLB": 12, "NHL": 4, "NASCAR": 7, "CBB": 7, "CFB": 12, "most": "NHL"}, "Sioux Falls(Mitchell) SD": {"NFL": 48, "NBA": 19, "MLB": 12, "NHL": 5, "NASCAR": 6, "CBB": 4, "CFB": 6, "most": "CBB"}, "South Bend-Elkhart IN": {"NFL": 32, "NBA": 21, "MLB": 15, "NHL": 5, "NASCAR": 7, "CBB": 9, "CFB": 12, "most": "NHL"}, "Spokane WA": {"NFL": 45, "NBA": 16, "MLB": 10, "NHL": 4, "NASCAR": 4, "CBB": 13, "CFB": 7, "most": "NHL"}, "Springfield MO": {"NFL": 38, "NBA": 18, "MLB": 20, "NHL": 4, "NASCAR": 7, "CBB": 4, "CFB": 7, "most": "NHL"}, "Springfield-Holyoke MA": {"NFL": 39, "NBA": 24, "MLB": 18, "NHL": 10, "NASCAR": 3, "CBB": 3, "CFB": 3, "most": "NASCAR"}, "St. Joseph MO": {"NFL": 42, "NBA": 18, "MLB": 22, "NHL": 2, "NASCAR": 5, "CBB": 5, "CFB": 6, "most": "NHL"}, "St. Louis MO": {"NFL": 32, "NBA": 18, "MLB": 25, "NHL": 11, "NASCAR": 4, "CBB": 4, "CFB": 5, "most": "NASCAR"}, "Syracuse NY": {"NFL": 38, "NBA": 23, "MLB": 14, "NHL": 9, "NASCAR": 6, "CBB": 6, "CFB": 5, "most": "CFB"}, "Tallahassee FL-Thomasville GA": {"NFL": 32, "NBA": 25, "MLB": 9, "NHL": 3, "NASCAR": 5, "CBB": 4, "CFB": 23, "most": "NHL"}, "Tampa-St. Petersburg (Sarasota) FL": {"NFL": 37, "NBA": 21, "MLB": 17, "NHL": 9, "NASCAR": 4, "CBB": 3, "CFB": 9, "most": "CBB"}, "Terre Haute IN": {"NFL": 38, "NBA": 21, "MLB": 18, "NHL": 3, "NASCAR": 9, "CBB": 6, "CFB": 5, "most": "NHL"}, "Toledo OH": {"NFL": 35, "NBA": 21, "MLB": 14, "NHL": 6, "NASCAR": 7, "CBB": 5, "CFB": 13, "most": "CBB"}, "Topeka KS": {"NFL": 37, "NBA": 18, "MLB": 19, "NHL": 2, "NASCAR": 5, "CBB": 9, "CFB": 10, "most": "NHL"}, "Traverse City-Cadillac MI": {"NFL": 31, "NBA": 15, "MLB": 18, "NHL": 11, "NASCAR": 8, "CBB": 8, "CFB": 10, "most": "NASCAR"}, "Tri-Cities TN-VA": {"NFL": 33, "NBA": 17, "MLB": 11, "NHL": 3, "NASCAR": 15, "CBB": 7, "CFB": 15, "most": "NHL"}, "Tucson (Sierra Vista) AZ": {"NFL": 39, "NBA": 21, "MLB": 13, "NHL": 4, "NASCAR": 3, "CBB": 15, "CFB": 6, "most": "NASCAR"}, "Tulsa OK": {"NFL": 33, "NBA": 28, "MLB": 11, "NHL": 3, "NASCAR": 5, "CBB": 4, "CFB": 16, "most": "NHL"}, "Twin Falls ID": {"NFL": 45, "NBA": 22, "MLB": 10, "NHL": 4, "NASCAR": 4, "CBB": 4, "CFB": 10, "most": "NHL"}, "Tyler-Longview(Lufkin & Nacogdoches) TX": {"NFL": 42, "NBA": 24, "MLB": 14, "NHL": 2, "NASCAR": 5, "CBB": 2, "CFB": 10, "most": "NHL"}, "Utica NY": {"NFL": 38, "NBA": 20, "MLB": 17, "NHL": 10, "NASCAR": 6, "CBB": 4, "CFB": 4, "most": "CBB"}, "Victoria TX": {"NFL": 45, "NBA": 30, "MLB": 10, "NHL": 2, "NASCAR": 4, "CBB": 2, "CFB": 7, "most": "NHL"}, "Waco-Temple-Bryan TX": {"NFL": 39, "NBA": 27, "MLB": 10, "NHL": 2, "NASCAR": 4, "CBB": 3, "CFB": 14, "most": "NHL"}, "Washington DC (Hagerstown MD)": {"NFL": 43, "NBA": 24, "MLB": 14, "NHL": 7, "NASCAR": 3, "CBB": 4, "CFB": 5, "most": "NASCAR"}, "Watertown NY": {"NFL": 39, "NBA": 16, "MLB": 14, "NHL": 16, "NASCAR": 8, "CBB": 3, "CFB": 4, "most": "CBB"}, "Wausau-Rhinelander WI": {"NFL": 49, "NBA": 14, "MLB": 15, "NHL": 6, "NASCAR": 8, "CBB": 3, "CFB": 5, "most": "CBB"}, "West Palm Beach-Ft. Pierce FL": {"NFL": 31, "NBA": 34, "MLB": 18, "NHL": 6, "NASCAR": 3, "CBB": 2, "CFB": 5, "most": "CBB"}, "Wheeling WV-Steubenville OH": {"NFL": 38, "NBA": 15, "MLB": 16, "NHL": 9, "NASCAR": 6, "CBB": 4, "CFB": 11, "most": "CBB"}, "Wichita Falls TX & Lawton OK": {"NFL": 40, "NBA": 26, "MLB": 12, "NHL": 2, "NASCAR": 5, "CBB": 3, "CFB": 12, "most": "NHL"}, "Wichita-Hutchinson KS": {"NFL": 42, "NBA": 21, "MLB": 13, "NHL": 3, "NASCAR": 5, "CBB": 9, "CFB": 8, "most": "NHL"}, "Wilkes Barre-Scranton PA": {"NFL": 43, "NBA": 16, "MLB": 16, "NHL": 7, "NASCAR": 8, "CBB": 3, "CFB": 7, "most": "CBB"}, "Wilmington NC": {"NFL": 40, "NBA": 20, "MLB": 12, "NHL": 5, "NASCAR": 8, "CBB": 9, "CFB": 7, "most": "NHL"}, "Yakima-Pasco-Richland-Kennewick WA": {"NFL": 52, "NBA": 19, "MLB": 11, "NHL": 3, "NASCAR": 3, "CBB": 4, "CFB": 7, "most": "NHL"}, "Youngstown OH": {"NFL": 41, "NBA": 23, "MLB": 15, "NHL": 5, "NASCAR": 5, "CBB": 3, "CFB": 8, "most": "CBB"}, "Yuma AZ-El Centro CA": {"NFL": 47, "NBA": 22, "MLB": 18, "NHL": 4, "NASCAR": 3, "CBB": 2, "CFB": 4, "most": "CBB"}, "Zanesville OH": {"NFL": 36, "NBA": 21, "MLB": 11, "NHL": 4, "NASCAR": 10, "CBB": 4, "CFB": 14, "most": "NHL"}}